{"type":"View","props":{"zOrder":3,"width":750,"name":"SkipSuccess_View","mouseThrough":false,"mouseEnabled":true,"height":1334},"compId":2,"child":[{"type":"Image","props":{"y":467,"x":125,"width":500,"skin":"Boomerang_UI/140.png","height":400,"centerY":0,"centerX":0},"compId":3,"child":[{"type":"Text","props":{"y":135,"x":17,"text":"恭喜您已成功跳过此次关卡","strokeColor":"#554f4f","stroke":3,"fontSize":38,"font":"SimHei","color":"#ffe000","bold":true,"runtime":"laya.display.Text"},"compId":5},{"type":"Image","props":{"width":300,"visible":true,"skin":"Boomerang_UI/排行榜及邀请好友通用按钮.png","sizeGrid":"20,30,40,30","scaleY":0.7,"scaleX":0.7,"name":"Confirm_Btn","height":130,"centerX":0,"bottom":49},"compId":6,"child":[{"type":"Image","props":{"y":28,"x":86,"skin":"Boomerang_UI/确定.png","scaleY":1.2,"scaleX":1.2},"compId":7}]}]},{"type":"Script","props":{"y":0,"x":0,"runtime":"script/MyView/SkipSuccess.ts"},"compId":9}],"loadList":["Boomerang_UI/140.png","Boomerang_UI/排行榜及邀请好友通用按钮.png","Boomerang_UI/确定.png"],"loadList3D":[]}